data_usage/__init__.py
pepephone_data-1.0.5.data/scripts/pepephone-data
pepephone_data-1.0.5.dist-info/LICENSE
pepephone_data-1.0.5.dist-info/METADATA
pepephone_data-1.0.5.dist-info/WHEEL
pepephone_data-1.0.5.dist-info/top_level.txt
pepephone_data-1.0.5.dist-info/RECORD
