Metadata-Version: 2.1
Name: pepephone-data
Version: 1.0.5
Summary: Shows Pepephone used and available data
Home-page: https://github.com/cpina/pepephone-data
Author: Carles Pina i Estany
Author-email: carles@pina.cat
License: UNKNOWN
Platform: UNKNOWN
Classifier: Programming Language :: Python :: 3
Classifier: License :: OSI Approved :: MIT License
Classifier: Operating System :: OS Independent
Requires-Python: >=3.6
Requires-Dist: requests
